destiny_sim/__init__.py
destiny_sim/agv/__init__.py
destiny_sim/agv/agv.py
destiny_sim/agv/fleet_manager.py
destiny_sim/agv/items.py
destiny_sim/agv/location.py
destiny_sim/agv/planning.py
destiny_sim/agv/site_graph.py
destiny_sim/agv/store_location.py
destiny_sim/builder/__init__.py
destiny_sim/builder/entity.py
destiny_sim/builder/runner.py
destiny_sim/builder/schema.py
destiny_sim/builder/entities/__init__.py
destiny_sim/builder/entities/human.py
destiny_sim/builder/entities/material_flow/__init__.py
destiny_sim/builder/entities/material_flow/buffer.py
destiny_sim/builder/entities/material_flow/manufacturing_cell.py
destiny_sim/builder/entities/material_flow/sink.py
destiny_sim/builder/entities/material_flow/source.py
destiny_sim/core/__init__.py
destiny_sim/core/environment.py
destiny_sim/core/metrics.py
destiny_sim/core/rendering.py
destiny_sim/core/simulation_entity.py
destiny_sim/core/timeline.py
destiny_sim-0.3.0.dist-info/METADATA
destiny_sim-0.3.0.dist-info/WHEEL
destiny_sim-0.3.0.dist-info/licenses/LICENSE
destiny_sim-0.3.0.dist-info/RECORD
