Metadata-Version: 2.4
Name: destiny-sim
Version: 0.3.0
Summary: Simpy based simulation engine with a visualization layer.
Project-URL: Homepage, https://github.com/deusXmachina-dev/DEStiny/tree/main/src/engine
Project-URL: Repository, https://github.com/deusXmachina-dev/DEStiny/tree/main/src/engine
Project-URL: Issues, https://github.com/deusXmachina-dev/DEStiny/issues
Author-email: deusXmachina Team <filip@deusxmachina.dev>
License: MIT License
License-File: LICENSE
Classifier: Development Status :: 3 - Alpha
Classifier: Intended Audience :: Developers
Classifier: License :: OSI Approved :: MIT License
Classifier: Programming Language :: Python :: 3
Classifier: Programming Language :: Python :: 3.11
Classifier: Programming Language :: Python :: 3.12
Classifier: Programming Language :: Python :: 3.13
Classifier: Topic :: Scientific/Engineering :: Interface Engine/Protocol Translator
Requires-Python: >=3.11
Requires-Dist: pydantic>=2.0.0
Requires-Dist: rustworkx>=0.17.1
Requires-Dist: simpy>=4.1.1
